{
  "extracted_text": "Guduru\n \nBala\n \nManikanta\n \nSai\n \nbalamanikanta.guduru@gmail.com\n   \n|\n  \n+91\n \n \n9440986516\n  \n|\n \nVijayawada,\n \nAndhra\n \npradesh\n \n,520010\n \ngithub/balamanikantsai\n \n  \n|\n \n \nlinkedin.com/in/balamanikantasai\n \n \n \nSummary\n \n \nDriven\n \ncomputer\n \nscience\n \nprofessional\n \nwith\n \nexpertise\n \nin\n \nsoftware\n \ndevelopment,\n \ndeep\n \nlearning,\n \nand\n \ncompetitive\n \nprogramming.\n \nFocused\n \non\n \ndesigning\n \nscalable\n \nsystems,\n \noptimizing\n \ncode\n \nperformance,\n \nand\n \nimproving\n \nefficiency\n \nacross\n \napplications.\n \nExperienced\n \nin\n \nleading\n \nand\n \ncollaborating\n \non\n \nimpactful\n \nprojects,\n \nwith\n \nresearch\n \npublications\n \nand\n \nhackathon\n \nsuccess.\n \nStrong\n \nfoundation\n \nin\n \nmathematics\n \nand\n \nproblem-solving,\n \nwith\n \na\n \npassion\n \nfor\n \nbuilding\n \nhigh-performance,\n \nreliable,\n \nand\n \nefficient\n \nAI-driven\n \nsolutions.\n \nProven\n \nleadership,\n \nadaptability,\n \nand\n \na\n \ncommitment\n \nto\n \ncontinuous\n \nlearning.\n \n \nEducation \n \nVIT-AP\n \nUniversity\n \n \n \n \n \n \n \n \n \n \n \n \n   \n2022\n \n–\n \n2026\n \nB.Tech.\n \nin\n \nComputer\n \nScience\n \nand\n \nEngineering\n \n \n \n \n \n \n \n  \nCGPA:\n \n9.39/10\n \nSri\n \nChaitanya\n \nJr.\n \nCollege,\n \nAndhra\n \nPradesh\n \n \n \n \n \n \n \n   \n2020\n \n–\n \n2022\n \nMPC\n \nStream,\n \nBoard\n \nof\n \nIntermediate\n \nEducation\n \n \n \n \n \n \n        \nPercentage:\n \n97.3%\n \nSri\n \nChaitanya\n \nTechno\n \nSchool\n \n \n \n \n \n \n \n \n \n   \n2019\n \n–\n \n2020\n \nSecondary\n \nBoard\n \nof\n \nEducation\n \n \n \n \n \n \n \n \n \n \nGPA:\n \n10.0/10.0\n \n \nSkills\n \nLanguages:\n \nJava,\n \nPython,\n \nC,\n \nJavaScript\n \nTools:\n \nGit,\n \nDocker,\n \nn8n,\n \nReplit\n \nDatabases:\n \nPostgreSQL,\n \nSQLite,\n \nMongoDB\n \nFrameworks:\n \nScikit-learn,\n \nNLTK,\n \nSpaCy,\n \nTensorFlow,\n \nFlask,\n \nLangChain\n \nPlatforms:\n \nRaspberry\n \nPi,\n \nArduino,\n \nWindows,\n \nLinux,\n \nAWS,\n \nGoogle\n \nCloud\n \nDomains:\n \nMachine\n \nLearning,\n \nNLP,\n \nWeb\n \nDevelopment,\n \nAgent\n \nDevelopment,\n \nDistributed\n \nStorage\n \nMethodologies:\n \nAgile,\n \nTeam\n \nCollaboration,\n \nProject\n \nManagement\n \n \nExperience\n \nContributor\n \n–\n \nRewear\n \n(via\n \nGSSoC)\n \n \n \n \n \n \n \n   \nJun\n \n2025\n \n–\n \nPresent\n \n●\n \nImproved\n \nfrontend\n \nand\n \nbackend\n \nmodules,\n \nmerging\n \n10+\n \npull\n \nrequests\n \nwith\n \nbug\n \nfixes\n \nand\n \nnew\n \nfeatures.\n \n●\n \nOptimized\n \ndatabase\n \nschema\n \nfor\n \nbetter\n \nquery\n \nefficiency\n \nand\n \nscalability.\n \n●\n \nCollaborated\n \nwith\n \ndistributed\n \ncontributors\n \nusing\n \nAgile\n \nworkflows\n \nand\n \nGit\n \nversion\n \ncontrol.\n \n \nProject\n \nWork\n \nAI-Based\n \nWarehouse\n \nSurveillance\n \nSystem\n \n(APSCSCL)\n \n●\n \nBuilt\n \nan\n \nAI-powered\n \nsurveillance\n \nsystem\n \nfor\n \ngunny\n \nbag\n \ncounting,\n \nvehicle/facial\n \nrecognition,\n \nand\n \nevent\n \ndetection,\n \nhandling\n \n20+\n \nCCTV\n \ncameras\n \nconcurrently.\n \n●\n \nDesigned\n \na\n \nscalable,\n \ncontainerized\n \narchitecture\n \nusing\n \nDocker,\n \nRabbitMQ,\n \nand\n \nMongoDB.\n \nCrystal\n \nClear\n \nVision:\n \nCataract\n \nPrediction\n \n(Transfer\n \nLearning)\n \n●\n \nFine-tuned\n \n6\n \ntransfer\n \nlearning\n \nmodels,\n \nachieving\n \n98.82%\n \nprecision\n \nin\n \ncataract\n \nprediction.\n \n●\n \nDeployed\n \nmodels\n \nvia\n \nFlask\n \nserver\n \nfor\n \nuser-friendly\n \naccess\n \nto\n \nmedical\n \nprofessionals.\n \nFederated\n \nLearning\n \non\n \nRaspberry\n \nPi\n \n4\n \n●\n \nDeployed\n \nfederated\n \nlearning\n \non\n \nRaspberry\n \nPi\n \n4\n \nfor\n \nprivacy-preserving\n \nneural\n \nnetwork\n \ntraining.\n \n●\n \nCo-authored\n \na\n \nreview\n \npaper\n \non\n \nfederated\n \nlearning\n \nin\n \nsmart\n \nagriculture,\n \nhighlighting\n \nsustainability\n \nbenefits\n \nwith\n \n15+\n \ncitations.\n \n \n \n \nOpen\n \nSource\n \n&\n \nCommunity\n \nEngagement\n \nVice\n \nPresident,\n \nSEDS\n \nVITAP,\n \nAmaravati\n \n \n \n \n \n \n       \nSep\n \n2023\n \n–\n \nPresent\n \n●\n \nAuthored\n \na\n \nresearch\n \npaper\n \non\n \nthe\n \nOort\n \nCloud,\n \nexploring\n \nits\n \nrole\n \nin\n \nsolar\n \nsystem\n \nevolution.\n \n●\n \nManaged\n \ntechnical\n \nfestivals,\n \ndriving\n \nparticipation\n \nof\n \n350+\n \nstudents.\n \nCampus\n \nAmbassador ,\n \nVIT-AP\n \n–\n \nGirlScript\n \nSummer\n \nof\n \nCode\n \n(GSSoC)\n \n                  \n \nJun\n \n2025\n \n–\n \nPresent\n \n●\n \nRepresented\n \nVIT-AP\n \nin\n \nthe\n \nGSSoC\n \ninitiative,\n \npromoting\n \nopen\n \nsource\n \nculture\n \nand\n \ncommunity\n \ninvolvement.\n \n●\n \nGuided\n \npeers\n \nin\n \ncontributing\n \nto\n \nbeginner-friendly\n \nrepositories,\n \nhelping\n \nnew\n \ncontributors\n \nmake\n \ntheir\n \nfirst\n \npull\n \nrequests.\n \n \nCertificates\n \nand\n \nAwards\n \n \n●\n \nMongoDB\n \nAssociate\n \nDatabase\n \nAdministrator\n \nCertification\n \n●\n \nAWS\n \nCertified\n \nCloud\n \nPractitioner\n \n(Issued\n \non\n \n19/07/2025)\n \n●\n \nIntroduction\n \nto\n \nComputer\n \nScience\n \n(CS50,\n \nHarvard\n \nUniversity)\n \n●\n \nArtificial\n \nIntelligence\n \nusing\n \nGoogle\n \nTensorFlow\n \n(SmartInternz)\n \n●\n \nPublished\n \n2\n \nresearch\n \npapers\n \nwith\n \n25\n \ncitations\n \n●\n \n1st\n \nplace\n \nat\n \nNASA\n \nSpace\n \nApps\n \nChallenge\n \nLocal\n \nEvent,\n \nAmaravathi\n \n \n \n ",
  "ai_parsed": {
    "name": "Guduru Bala Manikanta Sai",
    "email": "balamanikanta.guduru@gmail.com",
    "phone": "+91 9440986516",
    "skills": [
      "Java",
      "Python",
      "C",
      "JavaScript",
      "Git",
      "Docker",
      "n8n",
      "Replit",
      "PostgreSQL",
      "SQLite",
      "MongoDB",
      "Scikit-learn",
      "NLTK",
      "SpaCy",
      "TensorFlow",
      "Flask",
      "LangChain",
      "Raspberry Pi",
      "Arduino",
      "Windows",
      "Linux",
      "AWS",
      "Google Cloud",
      "Machine Learning",
      "NLP",
      "Web Development",
      "Agent Development",
      "Distributed Storage",
      "Agile",
      "Team Collaboration",
      "Project Management"
    ],
    "education": [
      "2022 – 2026 B.Tech. in Computer Science and Engineering, VIT-AP University, CGPA: 9.39/10",
      "2020 – 2022 MPC Stream, Sri Chaitanya Jr. College, Andhra Pradesh, Percentage: 97.3%",
      "2019 – 2020 Secondary Board of Education, Sri Chaitanya Techno School, GPA: 10.0/10.0"
    ],
    "experience": [
      {
        "role": "Contributor",
        "company": "Rewear (via GSSoC)",
        "years": "Jun 2025 – Present"
      },
      {
        "role": "Project Work AI-Based Warehouse Surveillance System (APSCSCL)",
        "company": null,
        "years": null
      },
      {
        "role": "Project Work Crystal Clear Vision: Cataract Prediction (Transfer Learning)",
        "company": null,
        "years": null
      },
      {
        "role": "Project Work Federated Learning on Raspberry Pi 4",
        "company": null,
        "years": null
      },
      {
        "role": "Vice President, SEDS VITAP, Amaravati",
        "company": "SEDS VITAP",
        "years": "Sep 2023 – Present"
      },
      {
        "role": "Campus Ambassador, VIT-AP – GirlScript Summer of Code (GSSoC)",
        "company": "VIT-AP – GirlScript Summer of Code (GSSoC)",
        "years": "Jun 2025 – Present"
      }
    ],
    "summary": "Driven computer science professional with expertise in software development, deep learning, and competitive programming. Focused on designing scalable systems, optimizing code performance, and improving efficiency across applications. Experienced in leading and collaborating on impactful projects, with research publications and hackathon success. Strong foundation in mathematics and problem-solving, with a passion for building high-performance, reliable, and efficient AI-driven solutions. Proven leadership, adaptability, and a commitment to continuous learning."
  }
}